wobble/__init__.py
wobble/__main__.py
wobble/wobble.py
wobble/dcos/__init__.py
wobble-0.0.2.dist-info/DESCRIPTION.rst
wobble-0.0.2.dist-info/entry_points.txt
wobble-0.0.2.dist-info/METADATA
wobble-0.0.2.dist-info/metadata.json
wobble-0.0.2.dist-info/RECORD
wobble-0.0.2.dist-info/top_level.txt
wobble-0.0.2.dist-info/WHEEL
