Metadata-Version: 2.0
Name: wobble
Version: 0.0.2
Summary: wobble: Deployment utility for DCOS+Marathon managed clusters
Home-page: UNKNOWN
Author: Matt Rasband
Author-email: matt.rasband@gmail.com
License: Apache-2.0
Platform: UNKNOWN
Classifier: Development Status :: 4 - Beta
Classifier: Environment :: Console
Classifier: Intended Audience :: Developers
Classifier: License :: OSI Approved :: Apache Software License
Classifier: Operating System :: POSIX
Classifier: Programming Language :: Python :: 3.5
Classifier: Programming Language :: Python :: 3 :: Only
Classifier: Topic :: Software Development
Classifier: Topic :: System :: Software Distribution
Classifier: Topic :: Utilities
Requires-Dist: requests (<3.0.0,>=2.0.0)
